aplot/__config__.py
aplot/__init__.py
aplot/code_utils.py
aplot/types.py
aplot/analysis/__init__.py
aplot/analysis/array_manipulation.py
aplot/analysis/qubit_specific.py
aplot/analysis/random.py
aplot/analysis/signal_analysis.py
aplot/animation/__init__.py
aplot/core/__init__.py
aplot/core/axes_class.py
aplot/core/axes_class.pyi
aplot/core/axes_list.py
aplot/core/axes_list.pyi
aplot/core/figure_class.py
aplot/core/front.py
aplot/core/front.pyi
aplot/core/typing.py
aplot/core/utils.py
aplot/plots/__init__.py
aplot/plots/display.py
aplot/plots/utils.py
aplot/styles/__init__.py
aplot-0.2.0.dist-info/LICENCE
aplot-0.2.0.dist-info/METADATA
aplot-0.2.0.dist-info/WHEEL
aplot-0.2.0.dist-info/top_level.txt
aplot-0.2.0.dist-info/RECORD
