Metadata-Version: 2.1
Name: aplot
Version: 0.2.0
Summary: Classical plots in one place.
Home-page: https://github.com/kyrylo-gr/aplot
Author: kyrylo.gr
Author-email: git@kyrylo.gr
Classifier: Programming Language :: Python :: 3
Classifier: Operating System :: OS Independent
Requires-Python: >=3.8
License-File: LICENCE
Requires-Dist: numpy
Requires-Dist: scipy
Requires-Dist: matplotlib
